setup.py
BinomialGauss/Binomialdistribution.py
BinomialGauss/Gaussiandistribution.py
BinomialGauss/Generaldistribution.py
BinomialGauss/__init__.py
BinomialGauss.egg-info/PKG-INFO
BinomialGauss.egg-info/SOURCES.txt
BinomialGauss.egg-info/dependency_links.txt
BinomialGauss.egg-info/not-zip-safe
BinomialGauss.egg-info/top_level.txt